pytennis/__init__.py
pytennis/_modidx.py
pytennis/_nbdev.py
pytennis/core.py
pytennis/data/__init__.py
pytennis/data/external.py
pytennis-0.0.2.dist-info/LICENSE
pytennis-0.0.2.dist-info/METADATA
pytennis-0.0.2.dist-info/WHEEL
pytennis-0.0.2.dist-info/entry_points.txt
pytennis-0.0.2.dist-info/top_level.txt
pytennis-0.0.2.dist-info/RECORD
