Metadata-Version: 2.1
Name: pytennis
Version: 0.0.2
Summary: A Python library for tennis data analysis.
Home-page: https://github.com/talktennisdata/pytennis/tree/master/
Author: Robert Seidl
Author-email: rob@talktennisdata.com
License: Apache Software License 2.0
Keywords: Tennis,Data Science
Classifier: Development Status :: 3 - Alpha
Classifier: Intended Audience :: Developers
Classifier: Natural Language :: English
Classifier: Programming Language :: Python :: 3.7
Classifier: Programming Language :: Python :: 3.8
Classifier: Programming Language :: Python :: 3.9
Classifier: Programming Language :: Python :: 3.10
Classifier: License :: OSI Approved :: Apache Software License
Requires-Python: >=3.7
License-File: LICENSE
Requires-Dist: fastdownload
Requires-Dist: pandas
Provides-Extra: dev
